mirage/__init__.py
mirage/cli.py
mirage/core/__init__.py
mirage/core/config.py
mirage/core/llm.py
mirage/core/prompts.py
mirage/embeddings/__init__.py
mirage/embeddings/models.py
mirage/embeddings/rerankers_multimodal.py
mirage/embeddings/rerankers_text.py
mirage/evaluation/__init__.py
mirage/evaluation/metrics.py
mirage/evaluation/metrics_optimized.py
mirage/pipeline/__init__.py
mirage/pipeline/chunker.py
mirage/pipeline/context.py
mirage/pipeline/deduplication.py
mirage/pipeline/domain.py
mirage/pipeline/pdf_processor.py
mirage/pipeline/qa_generator.py
mirage/utils/__init__.py
mirage/utils/ablation.py
mirage/utils/preflight.py
mirage/utils/stats.py
mirage_benchmark-1.0.5.dist-info/licenses/LICENSE
mirage_benchmark-1.0.5.dist-info/METADATA
mirage_benchmark-1.0.5.dist-info/WHEEL
mirage_benchmark-1.0.5.dist-info/entry_points.txt
mirage_benchmark-1.0.5.dist-info/top_level.txt
mirage_benchmark-1.0.5.dist-info/RECORD
