Metadata-Version: 2.4
Name: mirage-benchmark
Version: 1.0.5
Summary: A Multiagent Framework for Generating Multimodal Multihop QA Datasets for RAG Evaluation
Home-page: https://github.com/ChandanKSahu/MiRAGE
Author: MiRAGE Authors
Author-email: MiRAGE Authors <contact@example.com>
Maintainer-email: MiRAGE Authors <contact@example.com>
License: Apache-2.0
Project-URL: Homepage, https://github.com/ChandanKSahu/MiRAGE
Project-URL: Documentation, https://github.com/ChandanKSahu/MiRAGE#readme
Project-URL: Repository, https://github.com/ChandanKSahu/MiRAGE.git
Project-URL: Issues, https://github.com/ChandanKSahu/MiRAGE/issues
Keywords: rag,multimodal,qa,dataset,generation,llm,vlm,evaluation,benchmark
Classifier: Development Status :: 4 - Beta
Classifier: Intended Audience :: Developers
Classifier: Intended Audience :: Science/Research
Classifier: License :: OSI Approved :: Apache Software License
Classifier: Programming Language :: Python :: 3
Classifier: Programming Language :: Python :: 3.9
Classifier: Programming Language :: Python :: 3.10
Classifier: Programming Language :: Python :: 3.11
Classifier: Programming Language :: Python :: 3.12
Classifier: Topic :: Scientific/Engineering :: Artificial Intelligence
Classifier: Topic :: Software Development :: Libraries :: Python Modules
Requires-Python: >=3.9
License-File: LICENSE
Requires-Dist: torch>=2.0.0
Requires-Dist: faiss-cpu>=1.7.0
Requires-Dist: numpy>=1.21.0
Requires-Dist: Pillow>=9.0.0
Requires-Dist: transformers>=4.44.0
Requires-Dist: huggingface_hub>=0.16.0
Requires-Dist: tqdm>=4.65.0
Requires-Dist: pyyaml>=6.0
Requires-Dist: requests>=2.28.0
Requires-Dist: aiohttp>=3.8.0
Requires-Dist: sentence-transformers>=2.2.0
Requires-Dist: bertopic>=0.16.0
Requires-Dist: umap-learn>=0.5.0
Requires-Dist: pandas>=1.5.0
Requires-Dist: scikit-learn>=1.0.0
Provides-Extra: gpu
Requires-Dist: bitsandbytes>=0.43.0; extra == "gpu"
Requires-Dist: accelerate>=0.20.0; extra == "gpu"
Provides-Extra: pdf
Requires-Dist: docling>=2.0.0; extra == "pdf"
Requires-Dist: pypdfium2>=4.0.0; extra == "pdf"
Requires-Dist: matplotlib>=3.5.0; extra == "pdf"
Provides-Extra: eval
Requires-Dist: ragas>=0.1.0; extra == "eval"
Requires-Dist: datasets>=2.0.0; extra == "eval"
Requires-Dist: langchain-google-genai>=1.0.0; extra == "eval"
Requires-Dist: langchain-openai>=0.1.0; extra == "eval"
Provides-Extra: dev
Requires-Dist: pytest>=7.0.0; extra == "dev"
Requires-Dist: flake8>=5.0.0; extra == "dev"
Requires-Dist: black>=22.0.0; extra == "dev"
Requires-Dist: twine>=4.0.0; extra == "dev"
Requires-Dist: build>=0.10.0; extra == "dev"
Provides-Extra: all
Requires-Dist: bitsandbytes>=0.43.0; extra == "all"
Requires-Dist: accelerate>=0.20.0; extra == "all"
Requires-Dist: docling>=2.0.0; extra == "all"
Requires-Dist: pypdfium2>=4.0.0; extra == "all"
Requires-Dist: matplotlib>=3.5.0; extra == "all"
Requires-Dist: ragas>=0.1.0; extra == "all"
Requires-Dist: datasets>=2.0.0; extra == "all"
Requires-Dist: langchain-google-genai>=1.0.0; extra == "all"
Requires-Dist: langchain-openai>=0.1.0; extra == "all"
Requires-Dist: pytest>=7.0.0; extra == "all"
Requires-Dist: flake8>=5.0.0; extra == "all"
Requires-Dist: black>=22.0.0; extra == "all"
Dynamic: author
Dynamic: home-page
Dynamic: license-file
Dynamic: requires-python
